miraelogger/__init__.py
miraelogger-0.0.3.dist-info/METADATA
miraelogger-0.0.3.dist-info/WHEEL
miraelogger-0.0.3.dist-info/top_level.txt
miraelogger-0.0.3.dist-info/RECORD
