Metadata-Version: 2.1
Name: miraelogger
Version: 0.0.3
Summary: Custom logger for Jang, Mirae
Home-page: https://github.com/milktea0614/miraelogger
Author: Jang, Mirae
Author-email: milktea0614@naver.com
Keywords: pypi deploy,miraelogger
Classifier: Programming Language :: Python :: 3.10
Classifier: Programming Language :: Python :: 3.11
Requires-Python: >=3
